{
    "list": {
        "PageSize": 15,
        "PageIndex": 1,
        "RowCount": 384,
        "Items": [
            {
                "MicroBlog": {
                    "Id": 20092984,
                    "UserId": 21687,
                    "UserDisplayName": "Followme团队",
                    "OriginalId": 0,
                    "BlogBody": "我要一步一步往上爬     在最高点乘着叶片往前飞",
                    "ReplyCount": 4,
                    "ForwardedCount": 0,
                    "PraiseCount": 14,
                    "HasPhoto": false,
                    "HasVideo": false,
                    "HasMusic": false,
                    "PlatformId": null,
                    "SourceVersion": null,
                    "DeviceName": null,
                    "PostIP": null,
                    "AuditStatus": 1,
                    "PostType": 0,
                    "BlogTag": null,
                    "CreateDate": "\/Date(1476158771703)\/",
                    "Remark": "",
                    "longBlogId": 13180,
                    "ViewCount": 44,
                    "LongBlogTitle": "“重阳节”登山比赛活动剪影~~[鬼脸]",
                    "LongBlogIntro": "我要一步一步往上爬     在最高点乘着叶片往前飞",
                    "LongBlogImg": "http://file.followme.com/image.ashx?id=8b29e1d5-fb78-4e76-8495-f5f852b1b865\u0026w=80\u0026h=80\u0026centerCut=1",
                    "LongBlogBody": "",
                    "ModelStatus": 2
                },
                "IsPraise": false,
                "IsFavorites": false,
                "IsOwnerBlog": false,
                "IsAttention": false,
                "ReportTimeStr": "22小时前",
                "ImgUrlList": null,
                "AccountRole": 1,
                "UserType": 0,
                "UserTypeValue": "普通用户",
                "BrokerId": 3,
                "IsTop": false,
                "OriginalBlog": null
            },
            {
                "MicroBlog": {
                    "Id": 20092938,
                    "UserId": 74882,
                    "UserDisplayName": "VbcCrew",
                    "OriginalId": 0,
                    "BlogBody": "一哥们儿在建筑工地干活,有一次手握一米多长的钢筋狂追他一同事,一边追一边骂,门岗保安都没敢管,    \n...出去后两人就把钢筋卖了…\u003cimg src=\"/Scripts/User/face/傻笑.gif\" border=\"0\"/\u003e ",
                    "ReplyCount": 3,
                    "ForwardedCount": 0,
                    "PraiseCount": 6,
                    "HasPhoto": false,
                    "HasVideo": false,
                    "HasMusic": false,
                    "PlatformId": null,
                    "SourceVersion": null,
                    "DeviceName": null,
                    "PostIP": null,
                    "AuditStatus": 1,
                    "PostType": 0,
                    "BlogTag": null,
                    "CreateDate": "\/Date(1476153701982)\/",
                    "Remark": null,
                    "longBlogId": 0,
                    "ViewCount": 0,
                    "LongBlogTitle": null,
                    "LongBlogIntro": null,
                    "LongBlogImg": null,
                    "LongBlogBody": null,
                    "ModelStatus": 2
                },
                "IsPraise": false,
                "IsFavorites": false,
                "IsOwnerBlog": false,
                "IsAttention": false,
                "ReportTimeStr": "23小时前",
                "ImgUrlList": null,
                "AccountRole": 0,
                "UserType": 0,
                "UserTypeValue": "普通用户",
                "BrokerId": 3,
                "IsTop": false,
                "OriginalBlog": null
            },
            {
                "MicroBlog": {
                    "Id": 20093006,
                    "UserId": 76088,
                    "UserDisplayName": "一枝梨花",
                    "OriginalId": 0,
                    "BlogBody": "",
                    "ReplyCount": 2,
                    "ForwardedCount": 0,
                    "PraiseCount": 1,
                    "HasPhoto": true,
                    "HasVideo": false,
                    "HasMusic": false,
                    "PlatformId": null,
                    "SourceVersion": null,
                    "DeviceName": null,
                    "PostIP": null,
                    "AuditStatus": 1,
                    "PostType": 0,
                    "BlogTag": null,
                    "CreateDate": "\/Date(1476165912062)\/",
                    "Remark": null,
                    "longBlogId": 0,
                    "ViewCount": 0,
                    "LongBlogTitle": null,
                    "LongBlogIntro": null,
                    "LongBlogImg": null,
                    "LongBlogBody": null,
                    "ModelStatus": 2
                },
                "IsPraise": false,
                "IsFavorites": false,
                "IsOwnerBlog": false,
                "IsAttention": false,
                "ReportTimeStr": "20小时前",
                "ImgUrlList": [
                    "http://file1.followme.com/image.ashx?id=b4f69b05-724f-43b3-8a9e-4fd3680488ab\u0026w=80\u0026h=80\u0026centerCut=1"
                ],
                "AccountRole": 0,
                "UserType": 0,
                "UserTypeValue": "普通用户",
                "BrokerId": 3,
                "IsTop": false,
                "OriginalBlog": null
            },
            {
                "MicroBlog": {
                    "Id": 20093005,
                    "UserId": 29007,
                    "UserDisplayName": "Edi",
                    "OriginalId": 0,
                    "BlogBody": "天气变冷了，大家注意保暖，身体是革命的本钱。交易这一行，心脏不好可干不久滴。 ",
                    "ReplyCount": 2,
                    "ForwardedCount": 0,
                    "PraiseCount": 2,
                    "HasPhoto": false,
                    "HasVideo": false,
                    "HasMusic": false,
                    "PlatformId": null,
                    "SourceVersion": null,
                    "DeviceName": null,
                    "PostIP": null,
                    "AuditStatus": 1,
                    "PostType": 0,
                    "BlogTag": null,
                    "CreateDate": "\/Date(1476165307597)\/",
                    "Remark": null,
                    "longBlogId": 0,
                    "ViewCount": 0,
                    "LongBlogTitle": null,
                    "LongBlogIntro": null,
                    "LongBlogImg": null,
                    "LongBlogBody": null,
                    "ModelStatus": 2
                },
                "IsPraise": false,
                "IsFavorites": false,
                "IsOwnerBlog": false,
                "IsAttention": false,
                "ReportTimeStr": "20小时前",
                "ImgUrlList": null,
                "AccountRole": 0,
                "UserType": 1,
                "UserTypeValue": "交易员",
                "BrokerId": 1,
                "IsTop": false,
                "OriginalBlog": null
            },
            {
                "MicroBlog": {
                    "Id": 20093014,
                    "UserId": 74705,
                    "UserDisplayName": "王易耀",
                    "OriginalId": 0,
                    "BlogBody": "基本面解读沙特能源大臣KhalidAl-Falih周一表示，他将与OPEC...",
                    "ReplyCount": 1,
                    "ForwardedCount": 0,
                    "PraiseCount": 1,
                    "HasPhoto": false,
                    "HasVideo": false,
                    "HasMusic": false,
                    "PlatformId": null,
                    "SourceVersion": null,
                    "DeviceName": null,
                    "PostIP": null,
                    "AuditStatus": 1,
                    "PostType": 0,
                    "BlogTag": null,
                    "CreateDate": "\/Date(1476167251668)\/",
                    "Remark": "0",
                    "longBlogId": 13192,
                    "ViewCount": 2,
                    "LongBlogTitle": "王易耀：沙特俄罗斯态度乐观，冻产发酵强势支撑油价",
                    "LongBlogIntro": "基本面解读沙特能源大臣KhalidAl-Falih周一表示，他将与OPEC...",
                    "LongBlogImg": "http://blog.img.cnfol.com/images/5c/13/7989296/201610110210087570.jpg",
                    "LongBlogBody": "",
                    "ModelStatus": 2
                },
                "IsPraise": false,
                "IsFavorites": false,
                "IsOwnerBlog": false,
                "IsAttention": false,
                "ReportTimeStr": "20小时前",
                "ImgUrlList": null,
                "AccountRole": 2,
                "UserType": 0,
                "UserTypeValue": "普通用户",
                "BrokerId": 3,
                "IsTop": false,
                "OriginalBlog": null
            },
            {
                "MicroBlog": {
                    "Id": 20092952,
                    "UserId": 74020,
                    "UserDisplayName": "盛文兵",
                    "OriginalId": 0,
                    "BlogBody": "利空出尽美元继续高歌 股市收涨黄金短期回落",
                    "ReplyCount": 1,
                    "ForwardedCount": 1,
                    "PraiseCount": 0,
                    "HasPhoto": false,
                    "HasVideo": false,
                    "HasMusic": false,
                    "PlatformId": null,
                    "SourceVersion": null,
                    "DeviceName": null,
                    "PostIP": null,
                    "AuditStatus": 1,
                    "PostType": 0,
                    "BlogTag": null,
                    "CreateDate": "\/Date(1476155018853)\/",
                    "Remark": "",
                    "longBlogId": 13168,
                    "ViewCount": 1,
                    "LongBlogTitle": "英国脱欧持续打压英镑，黄金非美继续震荡下行为主",
                    "LongBlogIntro": "利空出尽美元继续高歌 股市收涨黄金短期回落",
                    "LongBlogImg": "http://file.followme.com/image.ashx?id=9c63694c-7465-423c-808f-223c84e23931\u0026w=80\u0026h=80\u0026centerCut=1",
                    "LongBlogBody": "",
                    "ModelStatus": 2
                },
                "IsPraise": false,
                "IsFavorites": false,
                "IsOwnerBlog": false,
                "IsAttention": false,
                "ReportTimeStr": "23小时前",
                "ImgUrlList": null,
                "AccountRole": 2,
                "UserType": 0,
                "UserTypeValue": "普通用户",
                "BrokerId": 3,
                "IsTop": false,
                "OriginalBlog": null
            },
            {
                "MicroBlog": {
                    "Id": 20092950,
                    "UserId": 75848,
                    "UserDisplayName": "徐薛龙金融分析师",
                    "OriginalId": 0,
                    "BlogBody": "【消息面】上周因国庆假期，上海黄金交易所休市，而国际市场的现货黄金价格却出...",
                    "ReplyCount": 1,
                    "ForwardedCount": 0,
                    "PraiseCount": 0,
                    "HasPhoto": false,
                    "HasVideo": false,
                    "HasMusic": false,
                    "PlatformId": null,
                    "SourceVersion": null,
                    "DeviceName": null,
                    "PostIP": null,
                    "AuditStatus": 1,
                    "PostType": 0,
                    "BlogTag": null,
                    "CreateDate": "\/Date(1476154525737)\/",
                    "Remark": "0",
                    "longBlogId": 13167,
                    "ViewCount": 0,
                    "LongBlogTitle": "徐薛龙：10.11金银多头趋势泯灭，逆袭时机在哪？",
                    "LongBlogIntro": "【消息面】上周因国庆假期，上海黄金交易所休市，而国际市场的现货黄金价格却出...",
                    "LongBlogImg": "http://blog.img.cnfol.com/images/c8/b1/8479134/201610111051178924.jpg",
                    "LongBlogBody": "",
                    "ModelStatus": 2
                },
                "IsPraise": false,
                "IsFavorites": false,
                "IsOwnerBlog": false,
                "IsAttention": false,
                "ReportTimeStr": "23小时前",
                "ImgUrlList": null,
                "AccountRole": 2,
                "UserType": 0,
                "UserTypeValue": "普通用户",
                "BrokerId": 3,
                "IsTop": false,
                "OriginalBlog": null
            },
            {
                "MicroBlog": {
                    "Id": 20092940,
                    "UserId": 74559,
                    "UserDisplayName": "徐晴媛",
                    "OriginalId": 0,
                    "BlogBody": "周一中国的买盘、黄金ETF重新流入及大跌后技术性的修复需求，给金价提供了支撑。而特朗普辩论表现提升，也重燃了市场避险情绪。然而，美元走强仍然令金价承压。 ",
                    "ReplyCount": 1,
                    "ForwardedCount": 0,
                    "PraiseCount": 0,
                    "HasPhoto": false,
                    "HasVideo": false,
                    "HasMusic": false,
                    "PlatformId": null,
                    "SourceVersion": null,
                    "DeviceName": null,
                    "PostIP": null,
                    "AuditStatus": 1,
                    "PostType": 0,
                    "BlogTag": null,
                    "CreateDate": "\/Date(1476153723231)\/",
                    "Remark": null,
                    "longBlogId": 0,
                    "ViewCount": 0,
                    "LongBlogTitle": null,
                    "LongBlogIntro": null,
                    "LongBlogImg": null,
                    "LongBlogBody": null,
                    "ModelStatus": 2
                },
                "IsPraise": false,
                "IsFavorites": false,
                "IsOwnerBlog": false,
                "IsAttention": false,
                "ReportTimeStr": "23小时前",
                "ImgUrlList": null,
                "AccountRole": 2,
                "UserType": 0,
                "UserTypeValue": "普通用户",
                "BrokerId": 3,
                "IsTop": false,
                "OriginalBlog": null
            },
            {
                "MicroBlog": {
                    "Id": 20093326,
                    "UserId": 28523,
                    "UserDisplayName": "带你飞",
                    "OriginalId": 20092952,
                    "BlogBody": "黄金抄底\u003cimg src=\"/Scripts/User/face/开心.gif\" border=\"0\"/\u003e",
                    "ReplyCount": 0,
                    "ForwardedCount": 0,
                    "PraiseCount": 0,
                    "HasPhoto": false,
                    "HasVideo": false,
                    "HasMusic": false,
                    "PlatformId": null,
                    "SourceVersion": null,
                    "DeviceName": null,
                    "PostIP": null,
                    "AuditStatus": 1,
                    "PostType": 0,
                    "BlogTag": null,
                    "CreateDate": "\/Date(1476239511649)\/",
                    "Remark": "",
                    "longBlogId": 0,
                    "ViewCount": 1,
                    "LongBlogTitle": "英国脱欧持续打压英镑，黄金非美继续震荡下行为主",
                    "LongBlogIntro": "利空出尽美元继续高歌 股市收涨黄金短期回落",
                    "LongBlogImg": "http://file.followme.com/image.ashx?id=9c63694c-7465-423c-808f-223c84e23931\u0026w=80\u0026h=80\u0026centerCut=1",
                    "LongBlogBody": "",
                    "ModelStatus": 2
                },
                "IsPraise": false,
                "IsFavorites": false,
                "IsOwnerBlog": true,
                "IsAttention": false,
                "ReportTimeStr": "25秒前",
                "ImgUrlList": null,
                "AccountRole": 0,
                "UserType": 0,
                "UserTypeValue": "普通用户",
                "BrokerId": 3,
                "IsTop": false,
                "OriginalBlog": {
                    "MicroBlog": {
                        "Id": 20092952,
                        "UserId": 74020,
                        "UserDisplayName": "盛文兵",
                        "OriginalId": 0,
                        "BlogBody": "利空出尽美元继续高歌 股市收涨黄金短期回落",
                        "ReplyCount": 1,
                        "ForwardedCount": 1,
                        "PraiseCount": 0,
                        "HasPhoto": false,
                        "HasVideo": false,
                        "HasMusic": false,
                        "PlatformId": null,
                        "SourceVersion": null,
                        "DeviceName": null,
                        "PostIP": null,
                        "AuditStatus": 1,
                        "PostType": 0,
                        "BlogTag": null,
                        "CreateDate": "\/Date(1476155018853)\/",
                        "Remark": "",
                        "longBlogId": 13168,
                        "ViewCount": 1,
                        "LongBlogTitle": "英国脱欧持续打压英镑，黄金非美继续震荡下行为主",
                        "LongBlogIntro": "利空出尽美元继续高歌 股市收涨黄金短期回落",
                        "LongBlogImg": "http://file.followme.com/image.ashx?id=9c63694c-7465-423c-808f-223c84e23931\u0026w=80\u0026h=80\u0026centerCut=1",
                        "LongBlogBody": "",
                        "ModelStatus": 2
                    },
                    "IsPraise": false,
                    "IsFavorites": false,
                    "IsOwnerBlog": false,
                    "IsAttention": false,
                    "ReportTimeStr": "23小时前",
                    "ImgUrlList": null,
                    "AccountRole": 2,
                    "UserType": 0,
                    "UserTypeValue": null,
                    "BrokerId": 3,
                    "IsTop": false,
                    "OriginalBlog": null
                }
            },
            {
                "MicroBlog": {
                    "Id": 20093325,
                    "UserId": 74559,
                    "UserDisplayName": "徐晴媛",
                    "OriginalId": 0,
                    "BlogBody": "【美联储9月FOMC会议纪要再掀狂澜，黄金大限将至？】周二公布的美国9月就...",
                    "ReplyCount": 0,
                    "ForwardedCount": 0,
                    "PraiseCount": 0,
                    "HasPhoto": false,
                    "HasVideo": false,
                    "HasMusic": false,
                    "PlatformId": null,
                    "SourceVersion": null,
                    "DeviceName": null,
                    "PostIP": null,
                    "AuditStatus": 1,
                    "PostType": 0,
                    "BlogTag": null,
                    "CreateDate": "\/Date(1476239497135)\/",
                    "Remark": "0",
                    "longBlogId": 13312,
                    "ViewCount": 0,
                    "LongBlogTitle": "【徐晴媛】美联储会议纪要刷新美指底线，黄金猪队友盯死1250",
                    "LongBlogIntro": "【美联储9月FOMC会议纪要再掀狂澜，黄金大限将至？】周二公布的美国9月就...",
                    "LongBlogImg": "http://i5.jrjimg.cn/201610/12/blog_attach/blog_attach_14762392598741.jpg",
                    "LongBlogBody": "",
                    "ModelStatus": 2
                },
                "IsPraise": false,
                "IsFavorites": false,
                "IsOwnerBlog": false,
                "IsAttention": false,
                "ReportTimeStr": "39秒前",
                "ImgUrlList": null,
                "AccountRole": 2,
                "UserType": 0,
                "UserTypeValue": "普通用户",
                "BrokerId": 3,
                "IsTop": false,
                "OriginalBlog": null
            },
            {
                "MicroBlog": {
                    "Id": 20093324,
                    "UserId": 73940,
                    "UserDisplayName": "DebbyLi",
                    "OriginalId": 0,
                    "BlogBody": "一线周边楼市刹车 环京区域小开发商扛不住在降价 ",
                    "ReplyCount": 0,
                    "ForwardedCount": 0,
                    "PraiseCount": 0,
                    "HasPhoto": false,
                    "HasVideo": false,
                    "HasMusic": false,
                    "PlatformId": null,
                    "SourceVersion": null,
                    "DeviceName": null,
                    "PostIP": null,
                    "AuditStatus": 1,
                    "PostType": 0,
                    "BlogTag": null,
                    "CreateDate": "\/Date(1476239453816)\/",
                    "Remark": null,
                    "longBlogId": 0,
                    "ViewCount": 0,
                    "LongBlogTitle": null,
                    "LongBlogIntro": null,
                    "LongBlogImg": null,
                    "LongBlogBody": null,
                    "ModelStatus": 2
                },
                "IsPraise": false,
                "IsFavorites": false,
                "IsOwnerBlog": false,
                "IsAttention": false,
                "ReportTimeStr": "1分钟前",
                "ImgUrlList": null,
                "AccountRole": 0,
                "UserType": 0,
                "UserTypeValue": "普通用户",
                "BrokerId": 3,
                "IsTop": false,
                "OriginalBlog": null
            },
            {
                "MicroBlog": {
                    "Id": 20093323,
                    "UserId": 73940,
                    "UserDisplayName": "DebbyLi",
                    "OriginalId": 0,
                    "BlogBody": "12日人民币中间价报6.7258贬值160点 连续3天刷新6年新低 ",
                    "ReplyCount": 0,
                    "ForwardedCount": 0,
                    "PraiseCount": 0,
                    "HasPhoto": false,
                    "HasVideo": false,
                    "HasMusic": false,
                    "PlatformId": null,
                    "SourceVersion": null,
                    "DeviceName": null,
                    "PostIP": null,
                    "AuditStatus": 1,
                    "PostType": 0,
                    "BlogTag": null,
                    "CreateDate": "\/Date(1476239412416)\/",
                    "Remark": null,
                    "longBlogId": 0,
                    "ViewCount": 0,
                    "LongBlogTitle": null,
                    "LongBlogIntro": null,
                    "LongBlogImg": null,
                    "LongBlogBody": null,
                    "ModelStatus": 2
                },
                "IsPraise": false,
                "IsFavorites": false,
                "IsOwnerBlog": false,
                "IsAttention": false,
                "ReportTimeStr": "2分钟前",
                "ImgUrlList": null,
                "AccountRole": 0,
                "UserType": 0,
                "UserTypeValue": "普通用户",
                "BrokerId": 3,
                "IsTop": false,
                "OriginalBlog": null
            },
            {
                "MicroBlog": {
                    "Id": 20093322,
                    "UserId": 74885,
                    "UserDisplayName": "VbfCrew",
                    "OriginalId": 0,
                    "BlogBody": "真正的高贵，在于慎独 ",
                    "ReplyCount": 0,
                    "ForwardedCount": 0,
                    "PraiseCount": 1,
                    "HasPhoto": false,
                    "HasVideo": false,
                    "HasMusic": false,
                    "PlatformId": null,
                    "SourceVersion": null,
                    "DeviceName": null,
                    "PostIP": null,
                    "AuditStatus": 1,
                    "PostType": 0,
                    "BlogTag": null,
                    "CreateDate": "\/Date(1476239304827)\/",
                    "Remark": null,
                    "longBlogId": 0,
                    "ViewCount": 0,
                    "LongBlogTitle": null,
                    "LongBlogIntro": null,
                    "LongBlogImg": null,
                    "LongBlogBody": null,
                    "ModelStatus": 2
                },
                "IsPraise": false,
                "IsFavorites": false,
                "IsOwnerBlog": false,
                "IsAttention": false,
                "ReportTimeStr": "3分钟前",
                "ImgUrlList": null,
                "AccountRole": 0,
                "UserType": 0,
                "UserTypeValue": "普通用户",
                "BrokerId": 3,
                "IsTop": false,
                "OriginalBlog": null
            },
            {
                "MicroBlog": {
                    "Id": 20093321,
                    "UserId": 28473,
                    "UserDisplayName": "mooie",
                    "OriginalId": 0,
                    "BlogBody": "\n                    中国外汇交易中心数据显示：北京时间10:00，美元/人民币参考汇率为6.7210\n                    ",
                    "ReplyCount": 0,
                    "ForwardedCount": 0,
                    "PraiseCount": 0,
                    "HasPhoto": false,
                    "HasVideo": false,
                    "HasMusic": false,
                    "PlatformId": null,
                    "SourceVersion": null,
                    "DeviceName": null,
                    "PostIP": null,
                    "AuditStatus": 1,
                    "PostType": 0,
                    "BlogTag": null,
                    "CreateDate": "\/Date(1476239282424)\/",
                    "Remark": null,
                    "longBlogId": 0,
                    "ViewCount": 0,
                    "LongBlogTitle": null,
                    "LongBlogIntro": null,
                    "LongBlogImg": null,
                    "LongBlogBody": null,
                    "ModelStatus": 2
                },
                "IsPraise": false,
                "IsFavorites": false,
                "IsOwnerBlog": false,
                "IsAttention": false,
                "ReportTimeStr": "4分钟前",
                "ImgUrlList": null,
                "AccountRole": 0,
                "UserType": 0,
                "UserTypeValue": "普通用户",
                "BrokerId": 3,
                "IsTop": false,
                "OriginalBlog": null
            },
            {
                "MicroBlog": {
                    "Id": 20093319,
                    "UserId": 74003,
                    "UserDisplayName": "花旗银行",
                    "OriginalId": 0,
                    "BlogBody": "加息前等待更多经济数据(包括劳动力市场状况)是合适之举。",
                    "ReplyCount": 0,
                    "ForwardedCount": 0,
                    "PraiseCount": 0,
                    "HasPhoto": false,
                    "HasVideo": false,
                    "HasMusic": false,
                    "PlatformId": null,
                    "SourceVersion": null,
                    "DeviceName": null,
                    "PostIP": null,
                    "AuditStatus": 1,
                    "PostType": 0,
                    "BlogTag": null,
                    "CreateDate": "\/Date(1476239186702)\/",
                    "Remark": "",
                    "longBlogId": 13311,
                    "ViewCount": 0,
                    "LongBlogTitle": "花旗：美联储纪要和零售数据不太可能坐实12月加息",
                    "LongBlogIntro": "加息前等待更多经济数据(包括劳动力市场状况)是合适之举。",
                    "LongBlogImg": "http://file.followme.com/image.ashx?id=1cb55aa4-ee09-42fd-815a-b50c42300a45\u0026w=80\u0026h=80\u0026centerCut=1",
                    "LongBlogBody": "",
                    "ModelStatus": 2
                },
                "IsPraise": false,
                "IsFavorites": false,
                "IsOwnerBlog": false,
                "IsAttention": false,
                "ReportTimeStr": "5分钟前",
                "ImgUrlList": null,
                "AccountRole": 2,
                "UserType": 0,
                "UserTypeValue": "普通用户",
                "BrokerId": 3,
                "IsTop": false,
                "OriginalBlog": null
            }
        ],
        "TotalPages": 26
    }
}